aliyunsdkga/__init__.py
aliyunsdkga/endpoint.py
aliyunsdkga/request/__init__.py
aliyunsdkga/request/v20191120/AddEntriesToAclRequest.py
aliyunsdkga/request/v20191120/AssociateAclsWithListenerRequest.py
aliyunsdkga/request/v20191120/AssociateAdditionalCertificatesWithListenerRequest.py
aliyunsdkga/request/v20191120/AttachDdosToAcceleratorRequest.py
aliyunsdkga/request/v20191120/AttachLogStoreToEndpointGroupRequest.py
aliyunsdkga/request/v20191120/BandwidthPackageAddAcceleratorRequest.py
aliyunsdkga/request/v20191120/BandwidthPackageRemoveAcceleratorRequest.py
aliyunsdkga/request/v20191120/ChangeResourceGroupRequest.py
aliyunsdkga/request/v20191120/ConfigEndpointProbeRequest.py
aliyunsdkga/request/v20191120/CreateAcceleratorRequest.py
aliyunsdkga/request/v20191120/CreateAclRequest.py
aliyunsdkga/request/v20191120/CreateApplicationMonitorRequest.py
aliyunsdkga/request/v20191120/CreateBandwidthPackageRequest.py
aliyunsdkga/request/v20191120/CreateBasicAccelerateIpEndpointRelationRequest.py
aliyunsdkga/request/v20191120/CreateBasicAccelerateIpEndpointRelationsRequest.py
aliyunsdkga/request/v20191120/CreateBasicAccelerateIpRequest.py
aliyunsdkga/request/v20191120/CreateBasicAcceleratorRequest.py
aliyunsdkga/request/v20191120/CreateBasicEndpointGroupRequest.py
aliyunsdkga/request/v20191120/CreateBasicEndpointRequest.py
aliyunsdkga/request/v20191120/CreateBasicEndpointsRequest.py
aliyunsdkga/request/v20191120/CreateBasicIpSetRequest.py
aliyunsdkga/request/v20191120/CreateCustomRoutingEndpointGroupDestinationsRequest.py
aliyunsdkga/request/v20191120/CreateCustomRoutingEndpointGroupsRequest.py
aliyunsdkga/request/v20191120/CreateCustomRoutingEndpointTrafficPoliciesRequest.py
aliyunsdkga/request/v20191120/CreateCustomRoutingEndpointsRequest.py
aliyunsdkga/request/v20191120/CreateDomainRequest.py
aliyunsdkga/request/v20191120/CreateEndpointGroupRequest.py
aliyunsdkga/request/v20191120/CreateEndpointGroupsRequest.py
aliyunsdkga/request/v20191120/CreateForwardingRulesRequest.py
aliyun_python_sdk_ga-1.0.19.dist-info/LICENSE
aliyun_python_sdk_ga-1.0.19.dist-info/METADATA
aliyun_python_sdk_ga-1.0.19.dist-info/WHEEL
aliyun_python_sdk_ga-1.0.19.dist-info/top_level.txt
aliyun_python_sdk_ga-1.0.19.dist-info/RECORD
